{
    "agents": [
        {
            "position": 0,
            "ships_destroyed": 22,
            "character_id": 95095428,
            "isk_destroyed": 4189203778.999999,
            "character_name": "Xee Yoona-451"
        },
        {
            "position": 0,
            "ships_destroyed": 14,
            "character_id": 1604363267,
            "isk_destroyed": 3016905501.0199995,
            "character_name": "Eridanii"
        },
        {
            "position": 0,
            "ships_destroyed": 10,
            "character_id": 987468952,
            "isk_destroyed": 1704591449.28,
            "character_name": "NoGo Rose"
        },
        {
            "position": 0,
            "ships_destroyed": 5,
            "character_id": 95229965,
            "isk_destroyed": 1775382169.0,
            "character_name": "Sabrez Haklar"
        },
        {
            "position": 0,
            "ships_destroyed": 5,
            "character_id": 90895417,
            "isk_destroyed": 717899650.7299999,
            "character_name": "Sister Fisterr"
        },
        {
            "position": 0,
            "ships_destroyed": 3,
            "character_id": 92605259,
            "isk_destroyed": 668576702.286,
            "character_name": "Norrin Zelkarr"
        },
        {
            "position": 0,
            "ships_destroyed": 2,
            "character_id": 1034496619,
            "isk_destroyed": 518727313.48,
            "character_name": "Tekou"
        },
        {
            "position": 0,
            "ships_destroyed": 6,
            "character_id": 584976954,
            "isk_destroyed": 145862759.93,
            "character_name": "Jerythas"
        },
        {
            "position": 0,
            "ships_destroyed": 5,
            "character_id": 95051074,
            "isk_destroyed": 165320828.37,
            "character_name": "togi yuki"
        },
        {
            "position": 0,
            "ships_destroyed": 3,
            "character_id": 93317595,
            "isk_destroyed": 210537693.126,
            "character_name": "Gillion Wyrddych"
        },
        {
            "position": 0,
            "ships_destroyed": 8,
            "character_id": 1149749832,
            "isk_destroyed": 52330647.86,
            "character_name": "Saladiin"
        },
        {
            "position": 0,
            "ships_destroyed": 1,
            "character_id": 93007709,
            "isk_destroyed": 350769825.02,
            "character_name": "Orianna Okanata"
        },
        {
            "position": 0,
            "ships_destroyed": 1,
            "character_id": 93532393,
            "isk_destroyed": 90878335,
            "character_name": "Ransom Odunen"
        },
        {
            "position": 0,
            "ships_destroyed": 1,
            "character_id": 93838416,
            "isk_destroyed": 43432047.38,
            "character_name": "Banshee Legend"
        },
        {
            "position": 0,
            "ships_destroyed": 1,
            "character_id": 94154468,
            "isk_destroyed": 22071756.42,
            "character_name": "Cap'n Rick Clusterbomb"
        },
        {
            "position": 0,
            "ships_destroyed": 1,
            "character_id": 95009795,
            "isk_destroyed": 7552123.51,
            "character_name": "Tasmine Cha-Tien"
        }
    ]
}