{
    "ships": [
        {
            "ships_destroyed": 286,
            "ship_type_id": 33470,
            "ship_name": "Stratios",
            "isk_destroyed": 47268147641.79768
        },
        {
            "ships_destroyed": 280,
            "ship_type_id": 12032,
            "ship_name": "Manticore",
            "isk_destroyed": 37974001997.43728
        },
        {
            "ships_destroyed": 163,
            "ship_type_id": 11377,
            "ship_name": "Nemesis",
            "isk_destroyed": 18060626544.445198
        },
        {
            "ships_destroyed": 123,
            "ship_type_id": 12038,
            "ship_name": "Purifier",
            "isk_destroyed": 16166389475.092197
        },
        {
            "ships_destroyed": 32,
            "ship_type_id": 11963,
            "ship_name": "Rapier",
            "isk_destroyed": 6991484598.816001
        },
        {
            "ships_destroyed": 57,
            "ship_type_id": 33468,
            "ship_name": "Astero",
            "isk_destroyed": 3485598414.145999
        },
        {
            "ships_destroyed": 50,
            "ship_type_id": 12034,
            "ship_name": "Hound",
            "isk_destroyed": 3652340107.25
        },
        {
            "ships_destroyed": 33,
            "ship_type_id": 11965,
            "ship_name": "Pilgrim",
            "isk_destroyed": 5035766703.889999
        },
        {
            "ships_destroyed": 26,
            "ship_type_id": 29336,
            "ship_name": "Scythe Fleet Issue",
            "isk_destroyed": 2700129561.7099996
        },
        {
            "ships_destroyed": 10,
            "ship_type_id": 643,
            "ship_name": "Armageddon",
            "isk_destroyed": 3599348029.89
        },
        {
            "ships_destroyed": 18,
            "ship_type_id": 35683,
            "ship_name": "Hecate",
            "isk_destroyed": 1290992323.502
        },
        {
            "ships_destroyed": 14,
            "ship_type_id": 29984,
            "ship_name": "Tengu",
            "isk_destroyed": 1325326129.26
        },
        {
            "ships_destroyed": 17,
            "ship_type_id": 22464,
            "ship_name": "Flycatcher",
            "isk_destroyed": 1050529738.4899999
        },
        {
            "ships_destroyed": 10,
            "ship_type_id": 4302,
            "ship_name": "Oracle",
            "isk_destroyed": 1521925463.97
        },
        {
            "ships_destroyed": 11,
            "ship_type_id": 22456,
            "ship_name": "Sabre",
            "isk_destroyed": 1336169044.5599997
        },
        {
            "ships_destroyed": 20,
            "ship_type_id": 34562,
            "ship_name": "Svipul",
            "isk_destroyed": 725043897.4799999
        },
        {
            "ships_destroyed": 10,
            "ship_type_id": 11957,
            "ship_name": "Falcon",
            "isk_destroyed": 1449552340.9459999
        },
        {
            "ships_destroyed": 6,
            "ship_type_id": 16229,
            "ship_name": "Brutix",
            "isk_destroyed": 1762656477.2200003
        },
        {
            "ships_destroyed": 8,
            "ship_type_id": 29988,
            "ship_name": "Proteus",
            "isk_destroyed": 1241871114.76
        },
        {
            "ships_destroyed": 14,
            "ship_type_id": 12013,
            "ship_name": "Broadsword",
            "isk_destroyed": 672622533.9759998
        },
        {
            "ships_destroyed": 7,
            "ship_type_id": 17722,
            "ship_name": "Vigilant",
            "isk_destroyed": 1126532304.3000002
        },
        {
            "ships_destroyed": 11,
            "ship_type_id": 17715,
            "ship_name": "Gila",
            "isk_destroyed": 695602281.8100001
        },
        {
            "ships_destroyed": 5,
            "ship_type_id": 22460,
            "ship_name": "Eris",
            "isk_destroyed": 1071428104.17
        },
        {
            "ships_destroyed": 12,
            "ship_type_id": 34317,
            "ship_name": "Confessor",
            "isk_destroyed": 428794001.78999996
        },
        {
            "ships_destroyed": 7,
            "ship_type_id": 11995,
            "ship_name": "Onyx",
            "isk_destroyed": 633234119.66
        },
        {
            "ships_destroyed": 6,
            "ship_type_id": 22436,
            "ship_name": "Widow",
            "isk_destroyed": 630631619.2700001
        },
        {
            "ships_destroyed": 3,
            "ship_type_id": 24692,
            "ship_name": "Abaddon",
            "isk_destroyed": 881328238.61
        },
        {
            "ships_destroyed": 3,
            "ship_type_id": 640,
            "ship_name": "Scorpion",
            "isk_destroyed": 881328238.61
        },
        {
            "ships_destroyed": 3,
            "ship_type_id": 644,
            "ship_name": "Typhoon",
            "isk_destroyed": 881328238.61
        },
        {
            "ships_destroyed": 3,
            "ship_type_id": 24696,
            "ship_name": "Harbinger",
            "isk_destroyed": 881328238.61
        },
        {
            "ships_destroyed": 6,
            "ship_type_id": 11999,
            "ship_name": "Vagabond",
            "isk_destroyed": 393208190.82
        },
        {
            "ships_destroyed": 3,
            "ship_type_id": 11194,
            "ship_name": "Kitsune",
            "isk_destroyed": 714951134.9399999
        },
        {
            "ships_destroyed": 5,
            "ship_type_id": 12023,
            "ship_name": "Deimos",
            "isk_destroyed": 425895649.3
        },
        {
            "ships_destroyed": 3,
            "ship_type_id": 12042,
            "ship_name": "Ishkur",
            "isk_destroyed": 662948943.4300001
        },
        {
            "ships_destroyed": 16,
            "ship_type_id": 17703,
            "ship_name": "Imperial Navy Slicer",
            "isk_destroyed": 112387033.26
        },
        {
            "ships_destroyed": 3,
            "ship_type_id": 626,
            "ship_name": "Vexor",
            "isk_destroyed": 573722787.55
        },
        {
            "ships_destroyed": 7,
            "ship_type_id": 24700,
            "ship_name": "Myrmidon",
            "isk_destroyed": 175449061.59
        },
        {
            "ships_destroyed": 1,
            "ship_type_id": 607,
            "ship_name": "Imicus",
            "isk_destroyed": 1107705659.49
        },
        {
            "ships_destroyed": 2,
            "ship_type_id": 24702,
            "ship_name": "Hurricane",
            "isk_destroyed": 518727313.48
        },
        {
            "ships_destroyed": 9,
            "ship_type_id": 11959,
            "ship_name": "Rook",
            "isk_destroyed": 74402404.28
        },
        {
            "ships_destroyed": 2,
            "ship_type_id": 22452,
            "ship_name": "Heretic",
            "isk_destroyed": 305094109.32
        },
        {
            "ships_destroyed": 1,
            "ship_type_id": 638,
            "ship_name": "Raven",
            "isk_destroyed": 584344536.67
        },
        {
            "ships_destroyed": 1,
            "ship_type_id": 633,
            "ship_name": "Celestis",
            "isk_destroyed": 584344536.67
        },
        {
            "ships_destroyed": 3,
            "ship_type_id": 17634,
            "ship_name": "Caracal Navy Issue",
            "isk_destroyed": 158585258.23
        },
        {
            "ships_destroyed": 1,
            "ship_type_id": 11176,
            "ship_name": "Crow",
            "isk_destroyed": 419954765.73
        },
        {
            "ships_destroyed": 3,
            "ship_type_id": 11969,
            "ship_name": "Arazu",
            "isk_destroyed": 126508177.7
        },
        {
            "ships_destroyed": 4,
            "ship_type_id": 32874,
            "ship_name": "Dragoon",
            "isk_destroyed": 71851909.39999999
        },
        {
            "ships_destroyed": 1,
            "ship_type_id": 16233,
            "ship_name": "Prophecy",
            "isk_destroyed": 271927770.63
        },
        {
            "ships_destroyed": 1,
            "ship_type_id": 624,
            "ship_name": "Maller",
            "isk_destroyed": 271927770.63
        },
        {
            "ships_destroyed": 2,
            "ship_type_id": 34828,
            "ship_name": "Jackdaw",
            "isk_destroyed": 92548162.7
        },
        {
            "ships_destroyed": 4,
            "ship_type_id": 16240,
            "ship_name": "Catalyst",
            "isk_destroyed": 42957855.84
        },
        {
            "ships_destroyed": 2,
            "ship_type_id": 17928,
            "ship_name": "Daredevil",
            "isk_destroyed": 85662663.21000001
        },
        {
            "ships_destroyed": 2,
            "ship_type_id": 33818,
            "ship_name": "Orthrus",
            "isk_destroyed": 79718310.57
        },
        {
            "ships_destroyed": 2,
            "ship_type_id": 17843,
            "ship_name": "Vexor Navy Issue",
            "isk_destroyed": 78876952.61
        },
        {
            "ships_destroyed": 2,
            "ship_type_id": 22430,
            "ship_name": "Sin",
            "isk_destroyed": 75946649.78
        },
        {
            "ships_destroyed": 1,
            "ship_type_id": 4308,
            "ship_name": "Talos",
            "isk_destroyed": 120938801.95
        },
        {
            "ships_destroyed": 3,
            "ship_type_id": 33816,
            "ship_name": "Garmur",
            "isk_destroyed": 30858898.349999998
        },
        {
            "ships_destroyed": 1,
            "ship_type_id": 650,
            "ship_name": "Nereus",
            "isk_destroyed": 71271164.65
        },
        {
            "ships_destroyed": 3,
            "ship_type_id": 627,
            "ship_name": "Thorax",
            "isk_destroyed": 23600199.900000002
        },
        {
            "ships_destroyed": 3,
            "ship_type_id": 608,
            "ship_name": "Atron",
            "isk_destroyed": 18156840.43
        },
        {
            "ships_destroyed": 2,
            "ship_type_id": 603,
            "ship_name": "Merlin",
            "isk_destroyed": 22113759.6
        },
        {
            "ships_destroyed": 1,
            "ship_type_id": 11172,
            "ship_name": "Helios",
            "isk_destroyed": 26883983.616
        },
        {
            "ships_destroyed": 3,
            "ship_type_id": 17924,
            "ship_name": "Succubus",
            "isk_destroyed": 5774358.62
        },
        {
            "ships_destroyed": 3,
            "ship_type_id": 593,
            "ship_name": "Tristan",
            "isk_destroyed": 3139269.21
        },
        {
            "ships_destroyed": 1,
            "ship_type_id": 17812,
            "ship_name": "Republic Fleet Firetail",
            "isk_destroyed": 8370022.05
        },
        {
            "ships_destroyed": 1,
            "ship_type_id": 602,
            "ship_name": "Kestrel",
            "isk_destroyed": 6487783.51
        },
        {
            "ships_destroyed": 1,
            "ship_type_id": 599,
            "ship_name": "Burst",
            "isk_destroyed": 5550012.33
        },
        {
            "ships_destroyed": 1,
            "ship_type_id": 17718,
            "ship_name": "Phantasm",
            "isk_destroyed": 5258343.78
        },
        {
            "ships_destroyed": 2,
            "ship_type_id": 16242,
            "ship_name": "Thrasher",
            "isk_destroyed": 2033522.27
        },
        {
            "ships_destroyed": 1,
            "ship_type_id": 11400,
            "ship_name": "Jaguar",
            "isk_destroyed": 3915944.63
        },
        {
            "ships_destroyed": 1,
            "ship_type_id": 20125,
            "ship_name": "Curse",
            "isk_destroyed": 2328355.78
        },
        {
            "ships_destroyed": 1,
            "ship_type_id": 585,
            "ship_name": "Slasher",
            "isk_destroyed": 1471597.48
        }
    ]
}