{
    "ships": [
        {
            "ships_destroyed": 596,
            "ship_type_id": 33470,
            "ship_name": "Stratios",
            "isk_destroyed": 61310497233.14187
        },
        {
            "ships_destroyed": 249,
            "ship_type_id": 12032,
            "ship_name": "Manticore",
            "isk_destroyed": 46611761177.70636
        },
        {
            "ships_destroyed": 163,
            "ship_type_id": 11377,
            "ship_name": "Nemesis",
            "isk_destroyed": 38042371115.04999
        },
        {
            "ships_destroyed": 134,
            "ship_type_id": 12034,
            "ship_name": "Hound",
            "isk_destroyed": 23670475245.326397
        },
        {
            "ships_destroyed": 212,
            "ship_type_id": 33468,
            "ship_name": "Astero",
            "isk_destroyed": 13882714961.271502
        },
        {
            "ships_destroyed": 104,
            "ship_type_id": 29988,
            "ship_name": "Proteus",
            "isk_destroyed": 16411819646.830004
        },
        {
            "ships_destroyed": 104,
            "ship_type_id": 29984,
            "ship_name": "Tengu",
            "isk_destroyed": 16354718133.760002
        },
        {
            "ships_destroyed": 51,
            "ship_type_id": 12038,
            "ship_name": "Purifier",
            "isk_destroyed": 11964835620.380003
        },
        {
            "ships_destroyed": 44,
            "ship_type_id": 11963,
            "ship_name": "Rapier",
            "isk_destroyed": 8892667914.31
        },
        {
            "ships_destroyed": 30,
            "ship_type_id": 11957,
            "ship_name": "Falcon",
            "isk_destroyed": 10952279577.880003
        },
        {
            "ships_destroyed": 121,
            "ship_type_id": 34562,
            "ship_name": "Svipul",
            "isk_destroyed": 2105139652.6159003
        },
        {
            "ships_destroyed": 33,
            "ship_type_id": 29990,
            "ship_name": "Loki",
            "isk_destroyed": 4373231667.610001
        },
        {
            "ships_destroyed": 21,
            "ship_type_id": 11965,
            "ship_name": "Pilgrim",
            "isk_destroyed": 4169234316.9200006
        },
        {
            "ships_destroyed": 19,
            "ship_type_id": 33816,
            "ship_name": "Garmur",
            "isk_destroyed": 2201949604.4299994
        },
        {
            "ships_destroyed": 8,
            "ship_type_id": 22430,
            "ship_name": "Sin",
            "isk_destroyed": 4780972496.65
        },
        {
            "ships_destroyed": 20,
            "ship_type_id": 11969,
            "ship_name": "Arazu",
            "isk_destroyed": 1689485909.9282
        },
        {
            "ships_destroyed": 44,
            "ship_type_id": 12021,
            "ship_name": "Phobos",
            "isk_destroyed": 766760697.3199999
        },
        {
            "ships_destroyed": 14,
            "ship_type_id": 29986,
            "ship_name": "Legion",
            "isk_destroyed": 2283258536.3199997
        },
        {
            "ships_destroyed": 18,
            "ship_type_id": 22456,
            "ship_name": "Sabre",
            "isk_destroyed": 1634323901.8263998
        },
        {
            "ships_destroyed": 31,
            "ship_type_id": 35683,
            "ship_name": "Hecate",
            "isk_destroyed": 773601344.3199997
        },
        {
            "ships_destroyed": 6,
            "ship_type_id": 627,
            "ship_name": "Thorax",
            "isk_destroyed": 2379459120.96
        },
        {
            "ships_destroyed": 8,
            "ship_type_id": 11198,
            "ship_name": "Stiletto",
            "isk_destroyed": 966526109.96
        },
        {
            "ships_destroyed": 5,
            "ship_type_id": 12017,
            "ship_name": "Devoter",
            "isk_destroyed": 1370584362.8600001
        },
        {
            "ships_destroyed": 32,
            "ship_type_id": 37456,
            "ship_name": "Maulus Navy Issue",
            "isk_destroyed": 143335884.67999998
        },
        {
            "ships_destroyed": 5,
            "ship_type_id": 11987,
            "ship_name": "Guardian",
            "isk_destroyed": 792815669.49
        },
        {
            "ships_destroyed": 8,
            "ship_type_id": 12013,
            "ship_name": "Broadsword",
            "isk_destroyed": 403090785.18
        },
        {
            "ships_destroyed": 7,
            "ship_type_id": 42685,
            "ship_name": "Sunesis",
            "isk_destroyed": 296582058.94
        },
        {
            "ships_destroyed": 2,
            "ship_type_id": 20125,
            "ship_name": "Curse",
            "isk_destroyed": 895163019.25
        },
        {
            "ships_destroyed": 14,
            "ship_type_id": 16242,
            "ship_name": "Thrasher",
            "isk_destroyed": 107576150.28
        },
        {
            "ships_destroyed": 1,
            "ship_type_id": 32305,
            "ship_name": "Armageddon Navy Issue",
            "isk_destroyed": 1364950450.2
        },
        {
            "ships_destroyed": 1,
            "ship_type_id": 4302,
            "ship_name": "Oracle",
            "isk_destroyed": 1364950450.2
        },
        {
            "ships_destroyed": 3,
            "ship_type_id": 16240,
            "ship_name": "Catalyst",
            "isk_destroyed": 360865765.7
        },
        {
            "ships_destroyed": 4,
            "ship_type_id": 37480,
            "ship_name": "Bifrost",
            "isk_destroyed": 262662011.88819999
        },
        {
            "ships_destroyed": 8,
            "ship_type_id": 593,
            "ship_name": "Tristan",
            "isk_destroyed": 111036718.43
        },
        {
            "ships_destroyed": 2,
            "ship_type_id": 12023,
            "ship_name": "Deimos",
            "isk_destroyed": 441489270.94
        },
        {
            "ships_destroyed": 3,
            "ship_type_id": 37483,
            "ship_name": "Magus",
            "isk_destroyed": 247526444.91820002
        },
        {
            "ships_destroyed": 3,
            "ship_type_id": 621,
            "ship_name": "Caracal",
            "isk_destroyed": 224500220.43
        },
        {
            "ships_destroyed": 8,
            "ship_type_id": 32872,
            "ship_name": "Algos",
            "isk_destroyed": 71889390.0311
        },
        {
            "ships_destroyed": 5,
            "ship_type_id": 34317,
            "ship_name": "Confessor",
            "isk_destroyed": 103384704.95
        },
        {
            "ships_destroyed": 3,
            "ship_type_id": 11192,
            "ship_name": "Buzzard",
            "isk_destroyed": 114051802.68
        },
        {
            "ships_destroyed": 4,
            "ship_type_id": 626,
            "ship_name": "Vexor",
            "isk_destroyed": 85070303.13
        },
        {
            "ships_destroyed": 2,
            "ship_type_id": 17922,
            "ship_name": "Ashimmu",
            "isk_destroyed": 162203543.34
        },
        {
            "ships_destroyed": 5,
            "ship_type_id": 11186,
            "ship_name": "Malediction",
            "isk_destroyed": 55320241.12
        },
        {
            "ships_destroyed": 6,
            "ship_type_id": 17812,
            "ship_name": "Republic Fleet Firetail",
            "isk_destroyed": 37597110.63
        },
        {
            "ships_destroyed": 2,
            "ship_type_id": 11194,
            "ship_name": "Kitsune",
            "isk_destroyed": 104523109.05
        },
        {
            "ships_destroyed": 5,
            "ship_type_id": 32880,
            "ship_name": "Venture",
            "isk_destroyed": 34230106.949999996
        },
        {
            "ships_destroyed": 1,
            "ship_type_id": 17715,
            "ship_name": "Gila",
            "isk_destroyed": 140631270.06
        },
        {
            "ships_destroyed": 3,
            "ship_type_id": 11172,
            "ship_name": "Helios",
            "isk_destroyed": 46358218.4
        },
        {
            "ships_destroyed": 2,
            "ship_type_id": 11961,
            "ship_name": "Huginn",
            "isk_destroyed": 68094638.64
        },
        {
            "ships_destroyed": 3,
            "ship_type_id": 33151,
            "ship_name": "Brutix Navy Issue",
            "isk_destroyed": 39239970.01
        },
        {
            "ships_destroyed": 2,
            "ship_type_id": 12005,
            "ship_name": "Ishtar",
            "isk_destroyed": 39190327.48
        },
        {
            "ships_destroyed": 1,
            "ship_type_id": 11188,
            "ship_name": "Anathema",
            "isk_destroyed": 73925191.25
        },
        {
            "ships_destroyed": 3,
            "ship_type_id": 594,
            "ship_name": "Incursus",
            "isk_destroyed": 22956389.34
        },
        {
            "ships_destroyed": 1,
            "ship_type_id": 11995,
            "ship_name": "Onyx",
            "isk_destroyed": 58092843.83
        },
        {
            "ships_destroyed": 2,
            "ship_type_id": 22436,
            "ship_name": "Widow",
            "isk_destroyed": 19425264.27
        },
        {
            "ships_destroyed": 1,
            "ship_type_id": 33697,
            "ship_name": "Prospect",
            "isk_destroyed": 37901332.58
        },
        {
            "ships_destroyed": 1,
            "ship_type_id": 11400,
            "ship_name": "Jaguar",
            "isk_destroyed": 28525831.46
        },
        {
            "ships_destroyed": 1,
            "ship_type_id": 608,
            "ship_name": "Atron",
            "isk_destroyed": 14659664.13
        },
        {
            "ships_destroyed": 1,
            "ship_type_id": 24702,
            "ship_name": "Hurricane",
            "isk_destroyed": 9161237.58
        },
        {
            "ships_destroyed": 1,
            "ship_type_id": 17841,
            "ship_name": "Federation Navy Comet",
            "isk_destroyed": 7642211.41
        },
        {
            "ships_destroyed": 2,
            "ship_type_id": 11182,
            "ship_name": "Cheetah",
            "isk_destroyed": 3138947.31
        },
        {
            "ships_destroyed": 2,
            "ship_type_id": 11184,
            "ship_name": "Crusader",
            "isk_destroyed": 2280721.76
        },
        {
            "ships_destroyed": 1,
            "ship_type_id": 602,
            "ship_name": "Kestrel",
            "isk_destroyed": 3821475.14
        },
        {
            "ships_destroyed": 1,
            "ship_type_id": 37481,
            "ship_name": "Pontifex",
            "isk_destroyed": 3088800.69
        },
        {
            "ships_destroyed": 1,
            "ship_type_id": 33820,
            "ship_name": "Barghest",
            "isk_destroyed": 2025565.14
        },
        {
            "ships_destroyed": 1,
            "ship_type_id": 644,
            "ship_name": "Typhoon",
            "isk_destroyed": 1572717.11
        },
        {
            "ships_destroyed": 1,
            "ship_type_id": 645,
            "ship_name": "Dominix",
            "isk_destroyed": 1019522.46
        },
        {
            "ships_destroyed": 1,
            "ship_type_id": 606,
            "ship_name": "Velator",
            "isk_destroyed": 50326.74
        },
        {
            "ships_destroyed": 1,
            "ship_type_id": 11387,
            "ship_name": "Hyena",
            "isk_destroyed": 10000
        },
        {
            "ships_destroyed": 1,
            "ship_type_id": 11190,
            "ship_name": "Sentinel",
            "isk_destroyed": 10000
        },
        {
            "ships_destroyed": 1,
            "ship_type_id": 22452,
            "ship_name": "Heretic",
            "isk_destroyed": 10000
        },
        {
            "ships_destroyed": 1,
            "ship_type_id": 22464,
            "ship_name": "Flycatcher",
            "isk_destroyed": 10000
        }
    ]
}